README.rst
setup.py
kvpio/__init__.py
kvpio/cli.py
kvpio_python.egg-info/PKG-INFO
kvpio_python.egg-info/SOURCES.txt
kvpio_python.egg-info/dependency_links.txt
kvpio_python.egg-info/entry_points.txt
kvpio_python.egg-info/not-zip-safe
kvpio_python.egg-info/requires.txt
kvpio_python.egg-info/top_level.txt
test/test_kvpio.py